MANIFEST.in
README.md
setup.py
extension/linux64/include/nabto_client_api.h
extension/linux64/lib/libnabto_client_api_static.a
extension/linux64/lib/libnabto_static_external.a
extension/mac64/include/nabto_client_api.h
extension/mac64/lib/libnabto_client_api_static.a
extension/mac64/lib/libnabto_static_external.a
extension/src/nabto.c
nabto_client/__init__.py
nabto_client/profile.py
nabto_client/session.py
nabto_client/tunnel.py
nabto_client.egg-info/PKG-INFO
nabto_client.egg-info/SOURCES.txt
nabto_client.egg-info/dependency_links.txt
nabto_client.egg-info/top_level.txt