Metadata-Version: 2.1
Name: nabto-client
Version: 1.0.0
Summary: Nabto Client Wrapper for Python
Home-page: https://www.nabto.com/developer
Author: Alexandru Gandrabur
Author-email: alexandru.gandrabur@tremend.com
License: MIT
Platform: UNKNOWN
Classifier: Programming Language :: Python :: 3.6
Classifier: Programming Language :: Python :: 3.7
Classifier: Programming Language :: Python :: 3.8
Classifier: Topic :: Internet :: WWW/HTTP
Classifier: Topic :: Internet :: WWW/HTTP :: Dynamic Content
Classifier: License :: OSI Approved :: MIT License
Requires-Python: >=3.6
